django_response_middleware/__init__.py
django_response_middleware/django_response_middleware.py
django_response_middleware/response_codes.py
django_response_middleware/response_data.py
django_response_middleware/utils/__init__.py
django_response_middleware/utils/type_conversion.py
django_response_mid-2.11.dist-info/METADATA
django_response_mid-2.11.dist-info/WHEEL
django_response_mid-2.11.dist-info/top_level.txt
django_response_mid-2.11.dist-info/zip-safe
django_response_mid-2.11.dist-info/RECORD
